{
  "demons": {
    "easy": [
      {
        "name": "The nightmare",
        "id": "13519"
      },
      {
        "name": "The lightning road",
        "id": "55520"
      },
      {
        "name": "Platinum adventure",
        "id": "5904109"
      },
      {
        "name": "Speed Racer",
        "id": "3543219"
      },
      {
        "name": "X",
        "id": "17235008"
      },
      {
        "name": "Death moon",
        "id": "8660411"
      },
      {
        "name": "Xstep v2",
        "id": "341613"
      },
      {
        "name": "Laser room",
        "id": "1777565"
      },
      {
        "name": "Dear nostalgists",
        "id": "18735780"
      },
      {
        "name": "Extinction",
        "id": "38427291"
      },
      {
        "name": "Ystep",
        "id": "70059"
      },
      {
        "name": "Crescendo",
        "id": "186646"
      },
      {
        "name": "Problematic",
        "id": "7116121"
      },
      {
        "name": "DeCode",
        "id": "2997354"
      },
      {
        "name": "Sidestep",
        "id": "18025697"
      },
      {
        "name": "Demon mixed",
        "id": "566659"
      },
      {
        "name": "Theory of every v2",
        "id": "369294"
      },
      {
        "name": "Ultra Paracosm",
        "id": "11588490"
      },
      {
        "name": "Impulse",
        "id": "393159"
      },
      {
        "name": "Demon Park",
        "id": "10109"
      },
      {
        "name": "Speed of light",
        "id": "5098465"
      },
      {
        "name": "Super Cycles",
        "id": "57730"
      },
      {
        "name": "Lights and thunder",
        "id": "848722"
      },
      {
        "name": "Demon Jumper",
        "id": "199761"
      },
      {
        "name": "Insomnia",
        "id": "3332936"
      },
      {
        "name": "Buck Force",
        "id": "1650666"
      },
      {
        "name": "Freedom",
        "id": "29247995"
      },
      {
        "name": "Retro circles",
        "id": "14000484"
      },
      {
        "name": "ABCDEFGHIJKLMNOPQRS",
        "id": "45932196"
      },
      {
        "name": "Hextec Flow",
        "id": "102765"
      },
      {
        "name": "Sky realm",
        "id": "214523"
      },
      {
        "name": "Invisible Clubstep",
        "id": "1347537"
      },
      {
        "name": "Blue Hell",
        "id": "11317271"
      },
      {
        "name": "Moon adventure",
        "id": "1474319"
      },
      {
        "name": "Chaoz Impact",
        "id": "3081555"
      },
      {
        "name": "Clutterfunk v2",
        "id": "358750"
      },
      {
        "name": "Infinite Circles",
        "id": "13037894"
      },
      {
        "name": "Motion",
        "id": "15619194"
      },
      {
        "name": "Extreme fantasy",
        "id": "135561"
      },
      {
        "name": "The Robotic Rush",
        "id": "11202046"
      },
      {
        "name": "Mirror Force",
        "id": "22390740"
      },
      {
        "name": "Impact X",
        "id": "28461869"
      },
      {
        "name": "Electroman Adven",
        "id": "428765"
      },
      {
        "name": "Spark",
        "id": "31076618"
      },
      {
        "name": "Radioactive Demon",
        "id": "497514"
      },
      {
        "name": "Adust",
        "id": "33244195"
      },
      {
        "name": "Dorabaedifficult4",
        "id": "2029133"
      },
      {
        "name": "Chaotic",
        "id": "840397"
      },
      {
        "name": "ISpyWithMyLittleEye",
        "id": "89886591"
      },
      {
        "name": "Horizon",
        "id": "14850167"
      },
      {
        "name": "Wild West",
        "id": "35472709"
      },
      {
        "name": "Flappy Weird",
        "id": "897987"
      }
    ]
  }
}